Metadata-Version: 2.1
Name: odoo-addon-base-kanban-stage-state
Version: 15.0.1.0.0.4
Summary: Maps stages from base_kanban_stage to states
Home-page: https://github.com/OCA/server-tools
Author: SMDrugstore, Odoo Community Association (OCA)
Author-email: support@odoo-community.org
License: LGPL-3
Platform: UNKNOWN
Classifier: Programming Language :: Python
Classifier: Framework :: Odoo
Classifier: Framework :: Odoo :: 15.0
Classifier: License :: OSI Approved :: GNU Lesser General Public License v3 (LGPLv3)
Requires-Python: >=3.8
Requires-Dist: odoo-addon-base-kanban-stage <15.1dev,>=15.0dev
Requires-Dist: odoo <15.1dev,>=15.0a
